{
  "game": "ot",
  "metric": "ev",
  "updated": "2026-05-06",
  "top10": [
    {
      "filename": "kelinimo_expectimax_fast.cpp",
      "commit": "12b7a92",
      "date": "2026-05-06",
      "aggregate_ev": 745.9936229497738,
      "games_per_cpu_s": 147.0,
      "setup_cpu_s": 130.931,
      "harness_elapsed_s": 10885.047,
      "n_threads": 20,
      "cpu_model": "13th Gen Intel(R) Core(TM) i7-13700K",
      "ev": 745.9936229497738
    }
  ],
  "by_variant": {
    "6": {
      "n_colors": 6,
      "top10": [
        {
          "filename": "kelinimo_expectimax_fast.cpp",
          "commit": "12b7a92",
          "date": "2026-05-06",
          "aggregate_ev": 745.9936229497738,
          "games_per_cpu_s": 147.0,
          "setup_cpu_s": 130.931,
          "harness_elapsed_s": 10885.047,
          "n_threads": 20,
          "cpu_model": "13th Gen Intel(R) Core(TM) i7-13700K",
          "n_colors": 6,
          "n_boards": 1194816,
          "ev": 655.7226,
          "stdev_ev": 116.3337,
          "avg_clicks": 17.3363,
          "stdev_clicks": 25.6195,
          "avg_ship_clicks": 11.7871,
          "stdev_ship_clicks": 2.2461,
          "perfect_rate": 0.3396,
          "all_ships_rate": 0.6977,
          "loss_5050_rate": 0.5063,
          "total_strategy_calls": 9399022
        }
      ]
    },
    "7": {
      "n_colors": 7,
      "top10": [
        {
          "filename": "kelinimo_expectimax_fast.cpp",
          "commit": "12b7a92",
          "date": "2026-05-06",
          "aggregate_ev": 745.9936229497738,
          "games_per_cpu_s": 147.0,
          "setup_cpu_s": 130.931,
          "harness_elapsed_s": 10885.047,
          "n_threads": 20,
          "cpu_model": "13th Gen Intel(R) Core(TM) i7-13700K",
          "n_colors": 7,
          "n_boards": 5672880,
          "ev": 943.2434,
          "stdev_ev": 322.0055,
          "avg_clicks": 17.7943,
          "stdev_clicks": 26.1268,
          "avg_ship_clicks": 13.1327,
          "stdev_ship_clicks": 2.7216,
          "perfect_rate": 0.2726,
          "all_ships_rate": 0.6475,
          "loss_5050_rate": 0.5325,
          "total_strategy_calls": 151557310
        }
      ]
    },
    "8": {
      "n_colors": 8,
      "top10": [
        {
          "filename": "kelinimo_expectimax_fast.cpp",
          "commit": "12b7a92",
          "date": "2026-05-06",
          "aggregate_ev": 745.9936229497738,
          "games_per_cpu_s": 147.0,
          "setup_cpu_s": 130.931,
          "harness_elapsed_s": 10885.047,
          "n_threads": 20,
          "cpu_model": "13th Gen Intel(R) Core(TM) i7-13700K",
          "n_colors": 8,
          "n_boards": 12328128,
          "ev": 1477.8407,
          "stdev_ev": 449.4718,
          "avg_clicks": 19.9307,
          "stdev_clicks": 28.9671,
          "avg_ship_clicks": 15.6984,
          "stdev_ship_clicks": 2.7221,
          "perfect_rate": 0.3614,
          "all_ships_rate": 0.7754,
          "loss_5050_rate": 0.4239,
          "total_strategy_calls": 906615796
        }
      ]
    },
    "9": {
      "n_colors": 9,
      "top10": [
        {
          "filename": "kelinimo_expectimax_fast.cpp",
          "commit": "12b7a92",
          "date": "2026-05-06",
          "aggregate_ev": 745.9936229497738,
          "games_per_cpu_s": 147.0,
          "setup_cpu_s": 130.931,
          "harness_elapsed_s": 10885.047,
          "n_threads": 20,
          "cpu_model": "13th Gen Intel(R) Core(TM) i7-13700K",
          "n_colors": 9,
          "n_boards": 12428080,
          "ev": 2154.7787,
          "stdev_ev": 196.2316,
          "avg_clicks": 23.2693,
          "stdev_clicks": 33.372,
          "avg_ship_clicks": 19.2318,
          "stdev_ship_clicks": 1.5645,
          "perfect_rate": 0.6584,
          "all_ships_rate": 0.9606,
          "loss_5050_rate": 0.2162,
          "total_strategy_calls": 1655503219
        }
      ]
    }
  }
}
